imufusion.cpython-39-darwin.so
imufusion-1.2.9.dist-info/RECORD
imufusion-1.2.9.dist-info/WHEEL
imufusion-1.2.9.dist-info/top_level.txt
imufusion-1.2.9.dist-info/METADATA
imufusion-1.2.9.dist-info/licenses/LICENSE.md
